nlp4bia/__init__.py
nlp4bia/datasets/Dataset.py
nlp4bia/datasets/__init__.py
nlp4bia/datasets/config.py
nlp4bia/datasets/benchmark/__init__.py
nlp4bia/datasets/benchmark/distemist.py
nlp4bia/datasets/benchmark/meddoplace.py
nlp4bia/datasets/benchmark/medprocner.py
nlp4bia/datasets/benchmark/symptemist.py
nlp4bia/datasets/utils/__init__.py
nlp4bia/datasets/utils/handlers.py
nlp4bia/datasets/utils/versions.py
nlp4bia/linking/BECELinker.py
nlp4bia/linking/__init__.py
nlp4bia/linking/rerankers.py
nlp4bia/linking/retrievers.py
nlp4bia/preprocessor/CSVConcatenator.py
nlp4bia/preprocessor/HashExtractor.py
nlp4bia/preprocessor/__init__.py
nlp4bia/preprocessor/deduplicator.py
nlp4bia/preprocessor/pdfparser.py
nlp4bia-2.4.4.dist-info/licenses/LICENSE
nlp4bia-2.4.4.dist-info/METADATA
nlp4bia-2.4.4.dist-info/WHEEL
nlp4bia-2.4.4.dist-info/top_level.txt
nlp4bia-2.4.4.dist-info/RECORD
