Metadata-Version: 2.4
Name: nlp4bia
Version: 2.4.4
Summary: Download NLP4BIA benchmarks and load datasets in their format
Author-email: Alberto Becerra <alberto.becerra.tome@gmail.com>
License: MIT License
Keywords: feed,reader,tutorial
Classifier: License :: OSI Approved :: MIT License
Classifier: Programming Language :: Python
Classifier: Programming Language :: Python :: 3
Requires-Python: >=3.7
License-File: LICENSE
Requires-Dist: pandas>=2.0.0
Requires-Dist: requests>=2.32.3
Requires-Dist: tqdm>=4.67.0
Requires-Dist: tomli; python_version < "3.11"
Requires-Dist: pymupdf4llm>=0.0.17
Requires-Dist: markdown>=3.3.4
Requires-Dist: sentence-transformers>=4.1.0
Requires-Dist: torch>=2.6.0
Provides-Extra: dev
Requires-Dist: black; extra == "dev"
Requires-Dist: bumpver; extra == "dev"
Requires-Dist: isort; extra == "dev"
Requires-Dist: pip-tools; extra == "dev"
Requires-Dist: pytest; extra == "dev"
Dynamic: license-file
